drfxtra/__init__.py
drfxtra/apps.py
drfxtra/factories.py
drfxtra/mixins.py
drfxtra/models.py
drfxtra/permissions.py
drfxtra/serializers.py
drfxtra/viewsets.py
drfxtra/templatetags/__init__.py
drfxtra/templatetags/defxtra.py
drfxtra-1.1.dist-info/DESCRIPTION.rst
drfxtra-1.1.dist-info/METADATA
drfxtra-1.1.dist-info/RECORD
drfxtra-1.1.dist-info/WHEEL
drfxtra-1.1.dist-info/metadata.json
drfxtra-1.1.dist-info/top_level.txt
